robopal/__init__.py
robopal/assets/__init__.py
robopal/assets/robot.xml
robopal/assets/__pycache__/__init__.cpython-311.pyc
robopal/assets/models/manipulators/DianaMed/DianaMed.urdf
robopal/assets/models/manipulators/DianaMed/DianaMed.xml
robopal/assets/models/manipulators/DianaMed/meshes/base_link.STL
robopal/assets/models/manipulators/DianaMed/meshes/cam.STL
robopal/assets/models/manipulators/DianaMed/meshes/cambase.STL
robopal/assets/models/manipulators/DianaMed/meshes/link1.STL
robopal/assets/models/manipulators/DianaMed/meshes/link2.STL
robopal/assets/models/manipulators/DianaMed/meshes/link3.STL
robopal/assets/models/manipulators/DianaMed/meshes/link4.STL
robopal/assets/models/manipulators/DianaMed/meshes/link5.STL
robopal/assets/models/manipulators/DianaMed/meshes/link6.STL
robopal/assets/models/manipulators/DianaMed/meshes/link7.STL
robopal/assets/models/manipulators/DianaMed/meshes/stick.STL
robopal/assets/models/manipulators/Panda/LICENSE
robopal/assets/models/manipulators/Panda/README.md
robopal/assets/models/manipulators/Panda/panda.png
robopal/assets/models/manipulators/Panda/panda.xml
robopal/assets/models/manipulators/Panda/scene.xml
robopal/assets/models/manipulators/Panda/meshes/link0.stl
robopal/assets/models/manipulators/Panda/meshes/link0_0.obj
robopal/assets/models/manipulators/Panda/meshes/link0_1.obj
robopal/assets/models/manipulators/Panda/meshes/link0_10.obj
robopal/assets/models/manipulators/Panda/meshes/link0_11.obj
robopal/assets/models/manipulators/Panda/meshes/link0_2.obj
robopal/assets/models/manipulators/Panda/meshes/link0_3.obj
robopal/assets/models/manipulators/Panda/meshes/link0_4.obj
robopal/assets/models/manipulators/Panda/meshes/link0_5.obj
robopal/assets/models/manipulators/Panda/meshes/link0_7.obj
robopal/assets/models/manipulators/Panda/meshes/link0_8.obj
robopal/assets/models/manipulators/Panda/meshes/link0_9.obj
robopal/assets/models/manipulators/Panda/meshes/link1.obj
robopal-0.4.1.dist-info/LICENSE
robopal-0.4.1.dist-info/METADATA
robopal-0.4.1.dist-info/WHEEL
robopal-0.4.1.dist-info/top_level.txt
robopal-0.4.1.dist-info/RECORD
