Metadata-Version: 2.1
Name: robopal
Version: 0.4.1
Summary: robopal: A Novel Simulation Framework based Mujoco
Home-page: https://github.com/NoneJou072/robopal
Author: Haoran Zhou, Yichao Huang, Yuhan Zhao, Yang Lu
Author-email: jou072@126.com
Classifier: License :: OSI Approved :: MIT License
Requires-Python: >=3.8
License-File: LICENSE
Requires-Dist: numpy >=1.23.5
Requires-Dist: mujoco >=3.1.4
Requires-Dist: gymnasium
Requires-Dist: rich
Provides-Extra: multi-agents
Requires-Dist: pettingzoo ; extra == 'multi-agents'
Provides-Extra: planning
Requires-Dist: ruckig ~=0.9.2 ; extra == 'planning'
